README.rst
setup.py
hpelefthandclient/__init__.py
hpelefthandclient/client.py
hpelefthandclient/exceptions.py
hpelefthandclient/http.py
hpelefthandclient/ssh.py
python_lefthandclient.egg-info/PKG-INFO
python_lefthandclient.egg-info/SOURCES.txt
python_lefthandclient.egg-info/dependency_links.txt
python_lefthandclient.egg-info/requires.txt
python_lefthandclient.egg-info/top_level.txt
test/test_HPELeftHandClient_Exception.py
test/test_HPELeftHandClient_MockSSH.py
test/test_HPELeftHandClient_base.py
test/test_HPELeftHandClient_server.py
test/test_HPELeftHandClient_system.py
test/test_HPELeftHandClient_volume.py