Metadata-Version: 1.1
Name: python-lefthandclient
Version: 2.1.0
Summary: HPE LeftHand/StoreVirtual HTTP REST Client
Home-page: http://packages.python.org/python-lefthandclient
Author: Kurt Martin
Author-email: kurt.f.martin@hpe.com
License: Apache License, Version 2.0
Keywords: hpe,lefthand,storevirtual,rest
Platform: UNKNOWN
Classifier: Development Status :: 3 - Alpha
Classifier: Intended Audience :: Developers
Classifier: License :: OSI Approved :: Apache Software License
Classifier: Environment :: Web Environment
Classifier: Programming Language :: Python
Classifier: Programming Language :: Python :: 2.6
Classifier: Programming Language :: Python :: 2.7
Classifier: Programming Language :: Python :: 3.4
Classifier: Topic :: Internet :: WWW/HTTP
Requires: paramiko
Requires: eventlet
Requires: requests
Provides: hplefthandclient
